README.rst
setup.py
modeldb/__init__.py
modeldb/__main__.py
modeldb/syncer.json
modeldb.egg-info/PKG-INFO
modeldb.egg-info/SOURCES.txt
modeldb.egg-info/dependency_links.txt
modeldb.egg-info/entry_points.txt
modeldb.egg-info/requires.txt
modeldb.egg-info/top_level.txt
modeldb/basic/ModelDbSyncerBase.py
modeldb/basic/Structs.py
modeldb/basic/__init__.py
modeldb/events/Event.py
modeldb/events/ExperimentEvent.py
modeldb/events/ExperimentRunEvent.py
modeldb/events/FitEvent.py
modeldb/events/GridSearchCVEvent.py
modeldb/events/MetricEvent.py
modeldb/events/PipelineEvent.py
modeldb/events/ProjectEvent.py
modeldb/events/RandomSplitEvent.py
modeldb/events/TransformEvent.py
modeldb/events/__init__.py
modeldb/sklearn_native/CrossValidationScore.py
modeldb/sklearn_native/GridCrossValidation.py
modeldb/sklearn_native/ModelDbSyncer.py
modeldb/sklearn_native/SyncableMetrics.py
modeldb/sklearn_native/SyncableRandomSplit.py
modeldb/sklearn_native/__init__.py
modeldb/thrift/__init__.py
modeldb/thrift/modeldb/ModelDBService.py
modeldb/thrift/modeldb/__init__.py
modeldb/thrift/modeldb/constants.py
modeldb/thrift/modeldb/ttypes.py
modeldb/utils/ConfigUtils.py
modeldb/utils/MetadataConstants.py
modeldb/utils/Singleton.py
modeldb/utils/__init__.py
samples/__init__.py
samples/sklearn/GridSearchCrossValidation.py
samples/sklearn/Iris-RandomForest.py
samples/sklearn/LabelEncoding.py
samples/sklearn/LinearModel.py
samples/sklearn/OneHotEncoding.py
samples/sklearn/OttoGroup-Calibration.py
samples/sklearn/Pipeline-AnovaFilter.py
samples/sklearn/Pipeline-CensusDataset.py
samples/sklearn/Pipeline-GridSearchCV.py
samples/sklearn/SimpleSample.py
samples/sklearn/SimpleSampleWithModelDB.py
samples/sklearn/Titanic-LogisticRegression.py
samples/sklearn/__init__.py