Metadata-Version: 1.1
Name: modeldb
Version: 0.0.1a30
Summary: A system to manage machine learning models
Home-page: https://github.com/mitdbg/modeldb/tree/master/client
Author: Manasi Vartak, MIT DB Group
Author-email: modeldb@csail.mit.edu
License: MIT
Keywords: machine learning ML model catalog
Platform: UNKNOWN
Classifier: Development Status :: 3 - Alpha
Classifier: Intended Audience :: Developers
Classifier: Intended Audience :: Science/Research
Classifier: Topic :: Scientific/Engineering
Classifier: License :: OSI Approved :: MIT License
Classifier: Programming Language :: Python :: 2.7
Classifier: Programming Language :: Python :: 3.5
